warhound/__init__.py
warhound/__version__.py
warhound/match.py
warhound/match_round.py
warhound/matchmaking.py
warhound/outcome.py
warhound/util.py
warhound-0.8.2.dist-info/DESCRIPTION.rst
warhound-0.8.2.dist-info/METADATA
warhound-0.8.2.dist-info/RECORD
warhound-0.8.2.dist-info/WHEEL
warhound-0.8.2.dist-info/metadata.json
warhound-0.8.2.dist-info/top_level.txt
