Metadata-Version: 2.0
Name: warhound
Version: 0.8.2
Summary: battlerite telemetry parser
Home-page: https://github.com/odeumgg/warhound
Author: Joshua Morris
Author-email: joshua.a.morris@gmail.com
License: MIT
Platform: UNKNOWN
Classifier: Development Status :: 4 - Beta
Classifier: Intended Audience :: Developers
Classifier: License :: OSI Approved :: MIT License
Classifier: Natural Language :: English
Classifier: Operating System :: MacOS :: MacOS X
Classifier: Operating System :: POSIX
Classifier: Operating System :: Microsoft :: Windows
Classifier: Programming Language :: Python
Classifier: Programming Language :: Python :: 3.6
Classifier: Programming Language :: Python :: 3.7
Classifier: Topic :: Software Development :: Libraries
Requires-Dist: simplejson (>=3.13.2)
